mhz19_async/__init__.py
mhz19_async/__main__.py
mhz19_async/mhz19.py
pymhz19_async-0.2.0.dist-info/LICENSE.txt
pymhz19_async-0.2.0.dist-info/METADATA
pymhz19_async-0.2.0.dist-info/WHEEL
pymhz19_async-0.2.0.dist-info/top_level.txt
pymhz19_async-0.2.0.dist-info/RECORD
