Metadata-Version: 2.1
Name: pymhz19-async
Version: 0.2.0
Summary: Python async library to interface with the MH-Z19* sensors for CO2.
Author-email: Lorenzo Pistone <blaffablaffa@gmail.com>
Project-URL: Homepage, https://github.com/pisto/pyMH-Z19_async
Keywords: MH-Z19,async,raspberry,serial,CO2,carbon dioxide
Classifier: Programming Language :: Python :: 3
Classifier: License :: OSI Approved :: MIT License
Classifier: Operating System :: OS Independent
Requires-Python: >=3.10
License-File: LICENSE.txt
Requires-Dist: aiofiles (~=23.1.0)
Requires-Dist: pyserial (~=3.5)
Requires-Dist: pyserial-asyncio (~=0.6)
